clsp/__init__.py
clsp/clsp.py
clsp/errors.py
clsp/solver.py
clsp/utils.py
pyclsp-1.9.0.dist-info/licenses/LICENSE
pyclsp-1.9.0.dist-info/METADATA
pyclsp-1.9.0.dist-info/WHEEL
pyclsp-1.9.0.dist-info/top_level.txt
pyclsp-1.9.0.dist-info/RECORD
