Metadata-Version: 2.4
Name: pyclsp
Version: 1.9.0
Summary: Modular Two-Step Convex Optimization Estimator for Ill-Posed Problems
Author-email: The Economist <29724411+econcz@users.noreply.github.com>
License-Expression: MIT
Project-URL: Homepage, https://github.com/econcz/pyclsp
Project-URL: Bug Tracker, https://github.com/econcz/pyclsp/issues
Keywords: estimators,convex-optimization,least-squares,generalized-inverse,regularization
Classifier: Programming Language :: Python :: 3
Classifier: Programming Language :: Python :: 3.10
Classifier: Programming Language :: Python :: 3.11
Classifier: Programming Language :: Python :: 3.12
Classifier: Operating System :: OS Independent
Classifier: Topic :: Scientific/Engineering :: Mathematics
Classifier: Topic :: Scientific/Engineering :: Information Analysis
Requires-Python: >=3.10
License-File: LICENSE
Requires-Dist: numpy>=1.24
Requires-Dist: scipy>=1.10
Requires-Dist: cvxpy>=1.3
Requires-Dist: ecos>=2.0
Requires-Dist: osqp>=0.6
Requires-Dist: scs>=3.2
Dynamic: license-file
